genetic_algorithms/__init__.py
genetic_algorithms/examples/example1_maximise_nums.py
genetic_algorithms/examples/example2_doors.py
genetic_algorithms/member.py
genetic_algorithms/population.py
genetic_algorithms/test/__init__.py
genetic_algorithms/test/test_e2e.py
genetic_algorithms/test/test_population.py
genetic_algorithms-1.0.1.dist-info/WHEEL
genetic_algorithms-1.0.1.dist-info/METADATA
genetic_algorithms-1.0.1.dist-info/RECORD
